mddatasetbuilder/__init__.py
mddatasetbuilder/__main__.py
mddatasetbuilder/_logger.py
mddatasetbuilder/_version.py
mddatasetbuilder/c_stack.cpp
mddatasetbuilder/c_stack.h
mddatasetbuilder/datasetbuilder.py
mddatasetbuilder/deepmd.py
mddatasetbuilder/detect.py
mddatasetbuilder/dps.pyd
mddatasetbuilder/dps.pyi
mddatasetbuilder/dps.pyx
mddatasetbuilder/py.typed
mddatasetbuilder/qmcalc.py
mddatasetbuilder/utils.py
mddatasetbuilder-1.3.10.dist-info/METADATA
mddatasetbuilder-1.3.10.dist-info/WHEEL
mddatasetbuilder-1.3.10.dist-info/entry_points.txt
mddatasetbuilder-1.3.10.dist-info/licenses/LICENSE
mddatasetbuilder-1.3.10.dist-info/RECORD
