Metadata-Version: 2.1
Name: mddatasetbuilder
Version: 1.3.10
Summary: A script to generate molecular dynamics (MD) datasets for machine learning from given LAMMPS trajectories automatically.
Keywords: dataset,molecular dynamics
Home-page: https://github.com/tongzhugroup/mddatasetbuilder
Author-Email: Jinzhe Zeng <jinzhe.zeng@rutgers.edu>
License:                    GNU LESSER GENERAL PUBLIC LICENSE
Classifier: Natural Language :: English
Classifier: Operating System :: POSIX :: Linux
Classifier: Operating System :: Microsoft :: Windows
Classifier: Programming Language :: Python :: 3.7
Classifier: Programming Language :: Python :: 3.8
Classifier: Programming Language :: Python :: 3.9
Classifier: Programming Language :: Python :: 3.10
Classifier: Programming Language :: Python :: 3.11
Classifier: Topic :: Scientific/Engineering :: Chemistry
Classifier: Topic :: Software Development :: Libraries :: Python Modules
Classifier: Topic :: Software Development :: Version Control :: Git
Project-URL: Homepage, https://github.com/tongzhugroup/mddatasetbuilder
Project-URL: Documentation, https://mddatasetbuilder.njzjz.win/
Project-URL: Repository, https://github.com/tongzhugroup/mddatasetbuilder
Requires-Python: >=3.7
Requires-Dist: numpy
Requires-Dist: scikit-learn
Requires-Dist: ase
Requires-Dist: gaussianrunner>=1.0.20
Requires-Dist: tqdm>=4.9.0
Requires-Dist: coloredlogs
Requires-Dist: lz4
Requires-Dist: dpdata>=0.1.2
Requires-Dist: openbabel-wheel>=3.1.0.0
Requires-Dist: requests; extra == "test"
Requires-Dist: pytest-sugar; extra == "test"
Requires-Dist: pytest-cov<4; extra == "test"
Requires-Dist: cython; extra == "test"
Requires-Dist: fakegaussian>=0.0.3; extra == "test"
Provides-Extra: test
